{
  "orgao": "DIRMAB",
  "orgaoNome": "Diretoria de Material Aeronáutico e Bélico",
  "atualizadoEm": "2026-06-17T14:34:51.162Z",
  "exercicios": [
    2026
  ],
  "exercicioPadrao": 2026,
  "execucao": [
    {
      "exercicio": 2026,
      "ao": "2048",
      "aoNome": "MANUTENCAO E SUPRIMENTO DE MATERIAL AERONAUTICO",
      "dotacao": 972988304,
      "recebido": 418492560.43,
      "empenhado": 238660087.18,
      "liquidado": 70576486.46,
      "pago": 49917135.88,
      "cambio": 0
    },
    {
      "exercicio": 2026,
      "ao": "20XV",
      "aoNome": "OPERACAO DO SISTEMA DE CONTROLE DO ESPACO AEREO BRASILEIRO -",
      "dotacao": 332196100,
      "recebido": 330795879.13,
      "empenhado": 321238052.93,
      "liquidado": 31938501.62,
      "pago": 31503749.04,
      "cambio": 811635.2
    },
    {
      "exercicio": 2026,
      "ao": "21A0",
      "aoNome": "APRESTAMENTO DAS FORCAS - MANUTENCAO DA PRONTIDAO E DA CAPAC",
      "dotacao": 97885531,
      "recebido": 37626356.41,
      "empenhado": 32750835.3,
      "liquidado": 266505.9,
      "pago": 266505.9,
      "cambio": 3753059.22
    },
    {
      "exercicio": 2026,
      "ao": "20IH",
      "aoNome": "MODERNIZACAO E REVITALIZACAO DE AERONAVES E SISTEMAS EMBARCA",
      "dotacao": 33099980,
      "recebido": 12186198.41,
      "empenhado": 8396033.51,
      "liquidado": 910429.69,
      "pago": 910429.69,
      "cambio": 810000
    }
  ],
  "creditoDiref": [
    {
      "exercicio": 2026,
      "ao": "2048",
      "nd": "339039",
      "ndNome": "OUTROS SERVICOS DE TERCEIROS - PESSOA JURIDICA",
      "fonte": "050",
      "ptres": "",
      "disponivel": 106015613.3
    },
    {
      "exercicio": 2026,
      "ao": "2048",
      "nd": "339030",
      "ndNome": "MATERIAL DE CONSUMO",
      "fonte": "050",
      "ptres": "",
      "disponivel": 72592007.52
    },
    {
      "exercicio": 2026,
      "ao": "20XV",
      "nd": "339039",
      "ndNome": "OUTROS SERVICOS DE TERCEIROS - PESSOA JURIDICA",
      "fonte": "052",
      "ptres": "",
      "disponivel": 4824334.34
    },
    {
      "exercicio": 2026,
      "ao": "20XV",
      "nd": "339030",
      "ndNome": "MATERIAL DE CONSUMO",
      "fonte": "052",
      "ptres": "",
      "disponivel": 4733491.87
    },
    {
      "exercicio": 2026,
      "ao": "21A0",
      "nd": "449052",
      "ndNome": "EQUIPAMENTOS E MATERIAL PERMANENTE",
      "fonte": "050",
      "ptres": "",
      "disponivel": 3824290.71
    },
    {
      "exercicio": 2026,
      "ao": "20IH",
      "nd": "339030",
      "ndNome": "MATERIAL DE CONSUMO",
      "fonte": "000",
      "ptres": "",
      "disponivel": 2222714.77
    },
    {
      "exercicio": 2026,
      "ao": "21A0",
      "nd": "339030",
      "ndNome": "MATERIAL DE CONSUMO",
      "fonte": "050",
      "ptres": "",
      "disponivel": 854270.24
    },
    {
      "exercicio": 2026,
      "ao": "20IH",
      "nd": "449052",
      "ndNome": "EQUIPAMENTOS E MATERIAL PERMANENTE",
      "fonte": "000",
      "ptres": "",
      "disponivel": 810000
    },
    {
      "exercicio": 2026,
      "ao": "20IH",
      "nd": "339039",
      "ndNome": "OUTROS SERVICOS DE TERCEIROS - PESSOA JURIDICA",
      "fonte": "000",
      "ptres": "",
      "disponivel": 757450.13
    },
    {
      "exercicio": 2026,
      "ao": "2048",
      "nd": "449052",
      "ndNome": "EQUIPAMENTOS E MATERIAL PERMANENTE",
      "fonte": "050",
      "ptres": "",
      "disponivel": 721932.11
    },
    {
      "exercicio": 2026,
      "ao": "2048",
      "nd": "449052",
      "ndNome": "EQUIPAMENTOS E MATERIAL PERMANENTE",
      "fonte": "051",
      "ptres": "",
      "disponivel": 296536.19
    },
    {
      "exercicio": 2026,
      "ao": "2048",
      "nd": "339030",
      "ndNome": "MATERIAL DE CONSUMO",
      "fonte": "000",
      "ptres": "",
      "disponivel": 201051.75
    },
    {
      "exercicio": 2026,
      "ao": "21A0",
      "nd": "339039",
      "ndNome": "OUTROS SERVICOS DE TERCEIROS - PESSOA JURIDICA",
      "fonte": "050",
      "ptres": "",
      "disponivel": 167523.01
    },
    {
      "exercicio": 2026,
      "ao": "21A0",
      "nd": "339030",
      "ndNome": "MATERIAL DE CONSUMO",
      "fonte": "000",
      "ptres": "",
      "disponivel": 29436.66
    },
    {
      "exercicio": 2026,
      "ao": "2048",
      "nd": "339039",
      "ndNome": "OUTROS SERVICOS DE TERCEIROS - PESSOA JURIDICA",
      "fonte": "000",
      "ptres": "",
      "disponivel": 5331.9
    },
    {
      "exercicio": 2026,
      "ao": "2048",
      "nd": "339000",
      "ndNome": "APLICACOES DIRETAS",
      "fonte": "000",
      "ptres": "",
      "disponivel": 0.48
    },
    {
      "exercicio": 2026,
      "ao": "21A0",
      "nd": "339000",
      "ndNome": "APLICACOES DIRETAS",
      "fonte": "000",
      "ptres": "",
      "disponivel": 0.28
    },
    {
      "exercicio": 2026,
      "ao": "21A0",
      "nd": "449052",
      "ndNome": "EQUIPAMENTOS E MATERIAL PERMANENTE",
      "fonte": "051",
      "ptres": "",
      "disponivel": 0.22
    }
  ],
  "creditoUGR": [
    {
      "exercicio": 2026,
      "codigo": "120038",
      "sigla": "120038",
      "nome": "DIRETORIA DE MATERIAL AERONAUTICO E BELICO",
      "ao": "2048",
      "disponivel": 167512225.22
    },
    {
      "exercicio": 2026,
      "codigo": "120049",
      "sigla": "120049",
      "nome": "PARQUE DE MATERIAL AERONAUTICO DO GALEAO",
      "ao": "20XV",
      "disponivel": 7575638.3
    },
    {
      "exercicio": 2026,
      "codigo": "120026",
      "sigla": "120026",
      "nome": "PARQUE MATERIAL AERONAUTICO DE LAGOA SANTA",
      "ao": "2048",
      "disponivel": 6813799.96
    },
    {
      "exercicio": 2026,
      "codigo": "120047",
      "sigla": "120047",
      "nome": "PARQUE DE MATERIAL BELICO DA AERONAUTICA",
      "ao": "21A0",
      "disponivel": 4637158.54
    },
    {
      "exercicio": 2026,
      "codigo": "120038",
      "sigla": "120038",
      "nome": "DIRETORIA DE MATERIAL AERONAUTICO E BELICO",
      "ao": "20IH",
      "disponivel": 2950694.09
    },
    {
      "exercicio": 2026,
      "codigo": "120049",
      "sigla": "120049",
      "nome": "PARQUE DE MATERIAL AERONAUTICO DO GALEAO",
      "ao": "2048",
      "disponivel": 1874577.55
    },
    {
      "exercicio": 2026,
      "codigo": "120082",
      "sigla": "120082",
      "nome": "BASE AEREA DE MANAUS",
      "ao": "2048",
      "disponivel": 1110140.7
    },
    {
      "exercicio": 2026,
      "codigo": "120631",
      "sigla": "120631",
      "nome": "BASE AEREA DE NATAL",
      "ao": "2048",
      "disponivel": 968007.65
    },
    {
      "exercicio": 2026,
      "codigo": "120026",
      "sigla": "120026",
      "nome": "PARQUE MATERIAL AERONAUTICO DE LAGOA SANTA",
      "ao": "20IH",
      "disponivel": 839470.81
    },
    {
      "exercicio": 2026,
      "codigo": "120038",
      "sigla": "120038",
      "nome": "DIRETORIA DE MATERIAL AERONAUTICO E BELICO",
      "ao": "20XV",
      "disponivel": 608893.09
    },
    {
      "exercicio": 2026,
      "codigo": "120068",
      "sigla": "120068",
      "nome": "PARQUE DE MATERIAL AERONAUTICO DE SAO PAULO",
      "ao": "20XV",
      "disponivel": 594480.85
    },
    {
      "exercicio": 2026,
      "codigo": "120026",
      "sigla": "120026",
      "nome": "PARQUE MATERIAL AERONAUTICO DE LAGOA SANTA",
      "ao": "20XV",
      "disponivel": 582713.97
    },
    {
      "exercicio": 2026,
      "codigo": "120643",
      "sigla": "120643",
      "nome": "BASE AEREA DE SANTA MARIA",
      "ao": "2048",
      "disponivel": 532302.53
    },
    {
      "exercicio": 2026,
      "codigo": "120075",
      "sigla": "120075",
      "nome": "BASE AEREA DE CANOAS",
      "ao": "2048",
      "disponivel": 348513.66
    },
    {
      "exercicio": 2026,
      "codigo": "120030",
      "sigla": "120030",
      "nome": "BASE AEREA DO GALEAO",
      "ao": "2048",
      "disponivel": 291521.89
    },
    {
      "exercicio": 2026,
      "codigo": "120038",
      "sigla": "120038",
      "nome": "DIRETORIA DE MATERIAL AERONAUTICO E BELICO",
      "ao": "21A0",
      "disponivel": 238362.29
    },
    {
      "exercicio": 2026,
      "codigo": "120091",
      "sigla": "120091",
      "nome": "COMISSAO AERONAUTICA BRASILEIRA NA EUROPA",
      "ao": "20XV",
      "disponivel": 196100
    },
    {
      "exercicio": 2026,
      "codigo": "120638",
      "sigla": "120638",
      "nome": "BASE AEREA DE CAMPO GRANDE",
      "ao": "2048",
      "disponivel": 141285.23
    },
    {
      "exercicio": 2026,
      "codigo": "120071",
      "sigla": "120071",
      "nome": "CENTRO LOGISTICO DA AERONAUTICA",
      "ao": "2048",
      "disponivel": 116794.05
    },
    {
      "exercicio": 2026,
      "codigo": "120004",
      "sigla": "120004",
      "nome": "BASE AEREA DE BRASILIA",
      "ao": "2048",
      "disponivel": 68387.63
    },
    {
      "exercicio": 2026,
      "codigo": "120068",
      "sigla": "120068",
      "nome": "PARQUE DE MATERIAL AERONAUTICO DE SAO PAULO",
      "ao": "2048",
      "disponivel": 42172.25
    },
    {
      "exercicio": 2026,
      "codigo": "120087",
      "sigla": "120087",
      "nome": "BASE AEREA DE BELEM",
      "ao": "2048",
      "disponivel": 12744.44
    }
  ],
  "restosAPagar": [
    {
      "exercicio": 2026,
      "tipo": "Não Processados",
      "sigla": "RPNP",
      "inscrito": 945660033.81,
      "cancelado": 3661276.78,
      "pago": 531472756.12,
      "liquidado": 534714791.3
    }
  ],
  "restosAPagarUGR": [
    {
      "exercicio": 2026,
      "codigo": "120049",
      "sigla": "120049",
      "nome": "PARQUE DE MATERIAL AERONAUTICO DO GALEAO",
      "ao": "2048",
      "aPagar": 137693679.89
    },
    {
      "exercicio": 2026,
      "codigo": "120068",
      "sigla": "120068",
      "nome": "PARQUE DE MATERIAL AERONAUTICO DE SAO PAULO",
      "ao": "2048",
      "aPagar": 83771848.75
    },
    {
      "exercicio": 2026,
      "codigo": "120026",
      "sigla": "120026",
      "nome": "PARQUE MATERIAL AERONAUTICO DE LAGOA SANTA",
      "ao": "2048",
      "aPagar": 36467856.18
    },
    {
      "exercicio": 2026,
      "codigo": "120047",
      "sigla": "120047",
      "nome": "PARQUE DE MATERIAL BELICO DA AERONAUTICA",
      "ao": "2048",
      "aPagar": 27296401.98
    },
    {
      "exercicio": 2026,
      "codigo": "120047",
      "sigla": "120047",
      "nome": "PARQUE DE MATERIAL BELICO DA AERONAUTICA",
      "ao": "21A0",
      "aPagar": 25485189.62
    },
    {
      "exercicio": 2026,
      "codigo": "120038",
      "sigla": "120038",
      "nome": "DIRETORIA DE MATERIAL AERONAUTICO E BELICO",
      "ao": "21H2",
      "aPagar": 20673753.69
    },
    {
      "exercicio": 2026,
      "codigo": "120026",
      "sigla": "120026",
      "nome": "PARQUE MATERIAL AERONAUTICO DE LAGOA SANTA",
      "ao": "20XV",
      "aPagar": 15919114.24
    },
    {
      "exercicio": 2026,
      "codigo": "120049",
      "sigla": "120049",
      "nome": "PARQUE DE MATERIAL AERONAUTICO DO GALEAO",
      "ao": "20XV",
      "aPagar": 15560271.1
    },
    {
      "exercicio": 2026,
      "codigo": "120026",
      "sigla": "120026",
      "nome": "PARQUE MATERIAL AERONAUTICO DE LAGOA SANTA",
      "ao": "20IH",
      "aPagar": 8676791.23
    },
    {
      "exercicio": 2026,
      "codigo": "120068",
      "sigla": "120068",
      "nome": "PARQUE DE MATERIAL AERONAUTICO DE SAO PAULO",
      "ao": "20XV",
      "aPagar": 8502753.07
    },
    {
      "exercicio": 2026,
      "codigo": "120038",
      "sigla": "120038",
      "nome": "DIRETORIA DE MATERIAL AERONAUTICO E BELICO",
      "ao": "20X7",
      "aPagar": 7578180.79
    },
    {
      "exercicio": 2026,
      "codigo": "120038",
      "sigla": "120038",
      "nome": "DIRETORIA DE MATERIAL AERONAUTICO E BELICO",
      "ao": "20YJ",
      "aPagar": 5713410.14
    },
    {
      "exercicio": 2026,
      "codigo": "120038",
      "sigla": "120038",
      "nome": "DIRETORIA DE MATERIAL AERONAUTICO E BELICO",
      "ao": "21EM",
      "aPagar": 2259261.2
    },
    {
      "exercicio": 2026,
      "codigo": "120038",
      "sigla": "120038",
      "nome": "DIRETORIA DE MATERIAL AERONAUTICO E BELICO",
      "ao": "20SP",
      "aPagar": 2094000
    },
    {
      "exercicio": 2026,
      "codigo": "120068",
      "sigla": "120068",
      "nome": "PARQUE DE MATERIAL AERONAUTICO DE SAO PAULO",
      "ao": "21H2",
      "aPagar": 1982872.46
    },
    {
      "exercicio": 2026,
      "codigo": "120038",
      "sigla": "120038",
      "nome": "DIRETORIA DE MATERIAL AERONAUTICO E BELICO",
      "ao": "2048",
      "aPagar": 1977843.35
    },
    {
      "exercicio": 2026,
      "codigo": "120038",
      "sigla": "120038",
      "nome": "DIRETORIA DE MATERIAL AERONAUTICO E BELICO",
      "ao": "21A0",
      "aPagar": 1941037.17
    },
    {
      "exercicio": 2026,
      "codigo": "120068",
      "sigla": "120068",
      "nome": "PARQUE DE MATERIAL AERONAUTICO DE SAO PAULO",
      "ao": "21E7",
      "aPagar": 1906948.78
    },
    {
      "exercicio": 2026,
      "codigo": "-8",
      "sigla": "-8",
      "nome": "SEM INFORMACAO",
      "ao": "21A0",
      "aPagar": 1717567.24
    },
    {
      "exercicio": 2026,
      "codigo": "120038",
      "sigla": "120038",
      "nome": "DIRETORIA DE MATERIAL AERONAUTICO E BELICO",
      "ao": "21GY",
      "aPagar": 896257.16
    },
    {
      "exercicio": 2026,
      "codigo": "120038",
      "sigla": "120038",
      "nome": "DIRETORIA DE MATERIAL AERONAUTICO E BELICO",
      "ao": "219C",
      "aPagar": 777376.38
    },
    {
      "exercicio": 2026,
      "codigo": "120071",
      "sigla": "120071",
      "nome": "CENTRO LOGISTICO DA AERONAUTICA",
      "ao": "2048",
      "aPagar": 414076.7
    },
    {
      "exercicio": 2026,
      "codigo": "120026",
      "sigla": "120026",
      "nome": "PARQUE MATERIAL AERONAUTICO DE LAGOA SANTA",
      "ao": "20X7",
      "aPagar": 351236.38
    },
    {
      "exercicio": 2026,
      "codigo": "120035",
      "sigla": "120035",
      "nome": "CENTRO DE TRANSPORTE LOGISTICO DA AERONAUTICA",
      "ao": "2048",
      "aPagar": 327457.05
    },
    {
      "exercicio": 2026,
      "codigo": "120038",
      "sigla": "120038",
      "nome": "DIRETORIA DE MATERIAL AERONAUTICO E BELICO",
      "ao": "20RM",
      "aPagar": 133690.55
    },
    {
      "exercicio": 2026,
      "codigo": "120038",
      "sigla": "120038",
      "nome": "DIRETORIA DE MATERIAL AERONAUTICO E BELICO",
      "ao": "20X1",
      "aPagar": 92133.59
    },
    {
      "exercicio": 2026,
      "codigo": "711000",
      "sigla": "711000",
      "nome": "GABINETE DO COMANDANTE DA MARINHA",
      "ao": "2000",
      "aPagar": 84052.68
    },
    {
      "exercicio": 2026,
      "codigo": "120038",
      "sigla": "120038",
      "nome": "DIRETORIA DE MATERIAL AERONAUTICO E BELICO",
      "ao": "20XV",
      "aPagar": 76223.83
    },
    {
      "exercicio": 2026,
      "codigo": "120026",
      "sigla": "120026",
      "nome": "PARQUE MATERIAL AERONAUTICO DE LAGOA SANTA",
      "ao": "2000",
      "aPagar": 53162.57
    },
    {
      "exercicio": 2026,
      "codigo": "120068",
      "sigla": "120068",
      "nome": "PARQUE DE MATERIAL AERONAUTICO DE SAO PAULO",
      "ao": "20X1",
      "aPagar": 40826.82
    },
    {
      "exercicio": 2026,
      "codigo": "120068",
      "sigla": "120068",
      "nome": "PARQUE DE MATERIAL AERONAUTICO DE SAO PAULO",
      "ao": "20X5",
      "aPagar": 35708.44
    },
    {
      "exercicio": 2026,
      "codigo": "120068",
      "sigla": "120068",
      "nome": "PARQUE DE MATERIAL AERONAUTICO DE SAO PAULO",
      "ao": "20X7",
      "aPagar": 8397.91
    },
    {
      "exercicio": 2026,
      "codigo": "120068",
      "sigla": "120068",
      "nome": "PARQUE DE MATERIAL AERONAUTICO DE SAO PAULO",
      "ao": "20YP",
      "aPagar": 8223.85
    },
    {
      "exercicio": 2026,
      "codigo": "120047",
      "sigla": "120047",
      "nome": "PARQUE DE MATERIAL BELICO DA AERONAUTICA",
      "ao": "2000",
      "aPagar": 7239.33
    },
    {
      "exercicio": 2026,
      "codigo": "120087",
      "sigla": "120087",
      "nome": "BASE AEREA DE BELEM",
      "ao": "2048",
      "aPagar": 1156.8
    }
  ],
  "execucaoUGR": [
    {
      "exercicio": 2026,
      "codigo": "120038",
      "sigla": "120038",
      "nome": "DIRETORIA DE MATERIAL AERONAUTICO E BELICO",
      "recebido": 235218154.42,
      "empenhado": 63907979.73,
      "liquidado": 2695317.7,
      "pago": 2695317.7
    },
    {
      "exercicio": 2026,
      "codigo": "120049",
      "sigla": "120049",
      "nome": "PARQUE DE MATERIAL AERONAUTICO DO GALEAO",
      "recebido": 228355485.07,
      "empenhado": 218905269.22,
      "liquidado": 37390444.52,
      "pago": 33747145.43
    },
    {
      "exercicio": 2026,
      "codigo": "120026",
      "sigla": "120026",
      "nome": "PARQUE MATERIAL AERONAUTICO DE LAGOA SANTA",
      "recebido": 159463020.53,
      "empenhado": 151227035.8,
      "liquidado": 36759589.38,
      "pago": 20315954.38
    },
    {
      "exercicio": 2026,
      "codigo": "120068",
      "sigla": "120068",
      "nome": "PARQUE DE MATERIAL AERONAUTICO DE SAO PAULO",
      "recebido": 138752582.79,
      "empenhado": 138115929.69,
      "liquidado": 26393515.7,
      "pago": 25402004.13
    },
    {
      "exercicio": 2026,
      "codigo": "120047",
      "sigla": "120047",
      "nome": "PARQUE DE MATERIAL BELICO DA AERONAUTICA",
      "recebido": 31360544.34,
      "empenhado": 26723385.8,
      "liquidado": 283136.28,
      "pago": 267478.78
    },
    {
      "exercicio": 2026,
      "codigo": "120082",
      "sigla": "120082",
      "nome": "BASE AEREA DE MANAUS",
      "recebido": 1110140.7,
      "empenhado": 0,
      "liquidado": 0,
      "pago": 0
    },
    {
      "exercicio": 2026,
      "codigo": "120631",
      "sigla": "120631",
      "nome": "BASE AEREA DE NATAL",
      "recebido": 1017245.01,
      "empenhado": 49237.36,
      "liquidado": 8270.25,
      "pago": 8270.25
    },
    {
      "exercicio": 2026,
      "codigo": "120091",
      "sigla": "120091",
      "nome": "COMISSAO AERONAUTICA BRASILEIRA NA EUROPA",
      "recebido": 778769.93,
      "empenhado": 582669.93,
      "liquidado": 0,
      "pago": 0
    },
    {
      "exercicio": 2026,
      "codigo": "120087",
      "sigla": "120087",
      "nome": "BASE AEREA DE BELEM",
      "recebido": 568353.02,
      "empenhado": 555608.58,
      "liquidado": 0,
      "pago": 0
    },
    {
      "exercicio": 2026,
      "codigo": "120643",
      "sigla": "120643",
      "nome": "BASE AEREA DE SANTA MARIA",
      "recebido": 532302.53,
      "empenhado": 0,
      "liquidado": 0,
      "pago": 0
    },
    {
      "exercicio": 2026,
      "codigo": "120071",
      "sigla": "120071",
      "nome": "CENTRO LOGISTICO DA AERONAUTICA",
      "recebido": 409690.6,
      "empenhado": 292896.55,
      "liquidado": 159799.07,
      "pago": 159799.07
    },
    {
      "exercicio": 2026,
      "codigo": "120075",
      "sigla": "120075",
      "nome": "BASE AEREA DE CANOAS",
      "recebido": 348513.66,
      "empenhado": 0,
      "liquidado": 0,
      "pago": 0
    },
    {
      "exercicio": 2026,
      "codigo": "120035",
      "sigla": "120035",
      "nome": "CENTRO DE TRANSPORTE LOGISTICO DA AERONAUTICA",
      "recebido": 345326.63,
      "empenhado": 345326.63,
      "liquidado": 0,
      "pago": 0
    },
    {
      "exercicio": 2026,
      "codigo": "120669",
      "sigla": "120669",
      "nome": "BASE AEREA DE SANTA CRUZ",
      "recebido": 331958.14,
      "empenhado": 331958.14,
      "liquidado": 0,
      "pago": 0
    },
    {
      "exercicio": 2026,
      "codigo": "120030",
      "sigla": "120030",
      "nome": "BASE AEREA DO GALEAO",
      "recebido": 291521.89,
      "empenhado": 0,
      "liquidado": 0,
      "pago": 0
    },
    {
      "exercicio": 2026,
      "codigo": "120638",
      "sigla": "120638",
      "nome": "BASE AEREA DE CAMPO GRANDE",
      "recebido": 141285.23,
      "empenhado": 0,
      "liquidado": 0,
      "pago": 0
    },
    {
      "exercicio": 2026,
      "codigo": "120004",
      "sigla": "120004",
      "nome": "BASE AEREA DE BRASILIA",
      "recebido": 68387.63,
      "empenhado": 0,
      "liquidado": 0,
      "pago": 0
    },
    {
      "exercicio": 2026,
      "codigo": "120624",
      "sigla": "120624",
      "nome": "BASE AEREA DE ANAPOLIS",
      "recebido": 7711.5,
      "empenhado": 7711.5,
      "liquidado": 1850.76,
      "pago": 1850.76
    }
  ]
}
